{
  "task_id": "studio_v2_shell_alpha_20260421",
  "lane_id": "main",
  "status": "done",
  "summary": "Added a separate /studio-v2 reader-first shell that keeps legacy /studio intact while reusing existing runtime bootstrap and note/ink/edited-card overlay contracts.",
  "outputs": [
    "presentation-ui/src/pages/StudioV2Page.tsx",
    "presentation-ui/src/pages/StudioV2Page.css",
    "presentation-ui/src/App.tsx"
  ],
  "validation": [
    {
      "command": "npm --prefix presentation-ui run build",
      "result": "passed"
    },
    {
      "command": "Select-String -Path presentation-ui/src/App.tsx -Pattern '/studio-v2|StudioV2Page'",
      "result": "passed"
    }
  ],
  "gaps": [
    "No live browser smoke on /studio-v2 yet"
  ]
}
